badgescale_ys_plt/__init__.py
badgescale_ys_plt/audio_playback.py
badgescale_ys_plt/bidirectional_convert_icon.png
badgescale_ys_plt/ble_wrapper.py
badgescale_ys_plt/http_file_server_wrapper.py
badgescale_ys_plt/iperf_wrapper.py
badgescale_ys_plt/main_window.py
badgescale_ys_plt/package_data.dat
badgescale_ys_plt/press_key_sample.wav
badgescale_ys_plt/proto_wrapper.py
badgescale_ys_plt/resource.py
badgescale_ys_plt/scan_qrcode_wrapper.py
badgescale_ys_plt/simple.py
badgescale_ys_plt/simple_http_server.py
badgescale_ys_plt/sn_csv_table_wrapper.py
badgescale_ys_plt/speaker_sample.wav
badgescale_ys_plt/summary_report_template.csv
badgescale_ys_plt/table_report.py
badgescale_ys_plt/iperf3/cygwin1.dll
badgescale_ys_plt/iperf3/iperf3.exe
badgescale_ys_plt/mic_utils/mic_uniformity_check.exe
badgescale_ys_plt/mic_utils/mic_uniformity_check_V1.1.exe
badgescale_ys_plt/mic_utils/vibration.wav
badgescale_ys_plt-13.0.data/data/badgescale_ys_plt_data/data_file
badgescale_ys_plt-13.0.dist-info/LICENSE.txt
badgescale_ys_plt-13.0.dist-info/METADATA
badgescale_ys_plt-13.0.dist-info/WHEEL
badgescale_ys_plt-13.0.dist-info/entry_points.txt
badgescale_ys_plt-13.0.dist-info/top_level.txt
badgescale_ys_plt-13.0.dist-info/RECORD
