Metadata-Version: 2.1
Name: badgescale-ys-plt
Version: 13.0
Summary: A production line tool project
Home-page: 
Author: Yebean
Author-email: bcui@bothlent.com
Project-URL: Bug Reports, https://github.com/pypa/sampleproject/issues
Project-URL: Funding, https://donate.pypi.org
Project-URL: Say Thanks!, http://saythanks.io/to/example
Project-URL: Source, https://github.com/pypa/sampleproject/
Keywords: badgescale,tool,test
Classifier: Development Status :: 3 - Alpha
Classifier: Intended Audience :: End Users/Desktop
Classifier: Topic :: Software Development :: Build Tools
Classifier: License :: OSI Approved :: MIT License
Classifier: Programming Language :: Python :: 3
Classifier: Programming Language :: Python :: 3.7
Classifier: Programming Language :: Python :: 3.8
Classifier: Programming Language :: Python :: 3.9
Classifier: Programming Language :: Python :: 3.10
Classifier: Programming Language :: Python :: 3 :: Only
Requires-Python: >=3.7, <4
License-File: LICENSE.txt
Requires-Dist: peppercorn
Requires-Dist: bleak
Requires-Dist: pysimplegui
Requires-Dist: pywinusb
Requires-Dist: numpy
Requires-Dist: psutil
Requires-Dist: pyserial
Requires-Dist: pyaudio
Requires-Dist: wave
Requires-Dist: pandas
Provides-Extra: dev
Requires-Dist: check-manifest ; extra == 'dev'
Provides-Extra: test
Requires-Dist: coverage ; extra == 'test'
